rpa_scada/__init__.py
rpa_scada/common.py
rpa_scada/utils.py
rpa_scada/GPM/__init__.py
rpa_scada/GPM/auth.py
rpa_scada/GPM/gpm.py
rpa_scada/GPM/reports.py
rpa_scada/GPM/utils.py
rpa_scada/QANTUM/__init__.py
rpa_scada/QANTUM/auth.py
rpa_scada/QANTUM/qantum.py
rpa_scada/QANTUM/reports.py
rpa_scada/QANTUM/utils.py
test/GPM_Quick_Query.py
test/__init__.py
test/utils.py
rpa_scada-1.0.2.dist-info/LICENCE
rpa_scada-1.0.2.dist-info/METADATA
rpa_scada-1.0.2.dist-info/WHEEL
rpa_scada-1.0.2.dist-info/top_level.txt
rpa_scada-1.0.2.dist-info/RECORD
