Metadata-Version: 2.1
Name: rpa-scada
Version: 1.0.2
Summary: Scraper of SCADAs without browser
Home-page: https://github.com/oym-tritec/rpa_scada
Author: Daniel Taiba
Author-email: danielt.dtr@gmail.com
Keywords: Scraper SCADA
License-File: LICENCE
Requires-Dist: numpy
Requires-Dist: pandas
Requires-Dist: requests
Requires-Dist: python-dotenv
